fastapi_easystart/__init__.py
fastapi_easystart/main.py
fastapi_easystart/app/__init__.py
fastapi_easystart/app/events.py
fastapi_easystart/app/commands/__init__.py
fastapi_easystart/app/commands/configure_main.py
fastapi_easystart/app/commands/favicon.ico
fastapi_easystart/app/commands/init.py
fastapi_easystart/app/commands/main.txt
fastapi_easystart/app/commands/test.py
fastapi_easystart/app/commands/init_files/__init__.py
fastapi_easystart/app/commands/init_files/config.py
fastapi_easystart/app/commands/init_files/routes.py
fastapi_easystart/app/commands/init_files/core/__init__.py
fastapi_easystart/app/commands/init_files/core/exception.py
fastapi_easystart/app/commands/init_files/core/middlewares.py
fastapi_easystart/app/commands/init_files/settings/__init__.py
fastapi_easystart/app/commands/init_files/settings/app.py
fastapi_easystart/app/commands/init_files/settings/cors.py
fastapi_easystart/app/commands/init_files/settings/swagger.py
fastapi_easystart/exceptions/__init__.py
fastapi_easystart/exceptions/authentication.py
fastapi_easystart/exceptions/base.py
fastapi_easystart/exceptions/common.py
fastapi_easystart/exceptions/database.py
fastapi_easystart/exceptions/permissions.py
fastapi_easystart/exceptions/throttling.py
fastapi_easystart/exceptions/token.py
fastapi_easystart/exceptions/enums/__init__.py
fastapi_easystart/exceptions/enums/auth.py
fastapi_easystart/exceptions/enums/database.py
fastapi_easystart/exceptions/enums/permissions.py
fastapi_easystart/exceptions/enums/response.py
fastapi_easystart/exceptions/enums/throttling.py
fastapi_easystart/exceptions/enums/token.py
fastapi_easystart/exceptions/handler/__init__.py
fastapi_easystart/exceptions/handler/custom_404_handler.py
fastapi_easystart/exceptions/handler/general_exception.py
fastapi_easystart/exceptions/handler/http_exception.py
fastapi_easystart/exceptions/handler/validation_exception.py
fastapi_easystart/exceptions/handler/value_error.py
fastapi_easystart/helpers/__init__.py
fastapi_easystart-0.0.7.dist-info/LICENSE
fastapi_easystart-0.0.7.dist-info/METADATA
fastapi_easystart-0.0.7.dist-info/WHEEL
fastapi_easystart-0.0.7.dist-info/top_level.txt
fastapi_easystart-0.0.7.dist-info/RECORD
