Metadata-Version: 2.1
Name: fastapi-easystart
Version: 0.0.7
Summary: FastAPI EasyStart simplifies FastAPI project setup with ready-to-use templates and configurations for environment management, CORS, and authentication. It lets you focus on coding by handling the boilerplate, making it easy to launch projects quickly.
Author-email: Ankaj Gupta <ankajgupta@coderwebsite.com>, Coder Website <contact@coderwebsite.com>
License: MIT
Keywords: fastapi,fastapi easy start,fastapi project setup,fastapi jwt,fastapi custom response,FastAPI projects,CORS setup,fastapi modular components
Classifier: Development Status :: 4 - Beta
Classifier: Environment :: Web Environment
Classifier: Intended Audience :: Developers
Classifier: License :: OSI Approved :: MIT License
Classifier: Operating System :: OS Independent
Classifier: Programming Language :: Python
Classifier: Programming Language :: Python :: 3.12
Requires-Python: >=3.12
License-File: LICENSE
Requires-Dist: rich
Requires-Dist: passlib
Requires-Dist: pyjwt
Requires-Dist: bson
Requires-Dist: fastapi
Requires-Dist: pydantic
Requires-Dist: uvicorn
Requires-Dist: pydantic-settings
